hier_backbone/__init__.py
hier_backbone/core.py
hier_backbone-0.9.0.dist-info/METADATA
hier_backbone-0.9.0.dist-info/WHEEL
hier_backbone-0.9.0.dist-info/top_level.txt
hier_backbone-0.9.0.dist-info/RECORD
